{
    "problems":[
        {"number":"1","answer":"C","url":"https://www.youtube-nocookie.com/embed/UsFCsRbYDyA?si=1WGn2Gb5bYBjx8M"},
        {"number":"2","answer":"E","url":"https://www.youtube-nocookie.com/embed/Lpc1W4SlLtQ?si=TRHTCpe2X8uQZY1Q"},
        {"number":"3","answer":"E","url":"https://www.youtube-nocookie.com/embed/UsFCsRbYDyA?si=1WGn2Gb5bYBjx8M"},
        {"number":"4","answer":"C","url":"https://www.youtube-nocookie.com/embed/UsFCsRbYDyA?si=1WGn2Gb5bYBjx8M"},
        {"number":"5","answer":"C","url":"https://www.youtube-nocookie.com/embed/UsFCsRbYDyA?si=1WGn2Gb5bYBjx8M"},
        {"number":"6","answer":"A","url":"https://www.youtube-nocookie.com/embed/UsFCsRbYDyA?si=1WGn2Gb5bYBjx8M"},
        {"number":"7","answer":"B","url":"https://www.youtube-nocookie.com/embed/UsFCsRbYDyA?si=1WGn2Gb5bYBjx8M"},
        {"number":"8","answer":"C","url":"https://www.youtube-nocookie.com/embed/UsFCsRbYDyA?si=1WGn2Gb5bYBjx8M"},
        {"number":"9","answer":"E","url":"https://www.youtube-nocookie.com/embed/UsFCsRbYDyA?si=1WGn2Gb5bYBjx8M"},
        {"number":"10","answer":"D","url":"https://www.youtube-nocookie.com/embed/UsFCsRbYDyA?si=1WGn2Gb5bYBjx8M"},
        {"number":"11","answer":"B","url":"https://www.youtube-nocookie.com/embed/UsFCsRbYDyA?si=1WGn2Gb5bYBjx8M"},
        {"number":"12","answer":"B","url":"https://www.youtube-nocookie.com/embed/UsFCsRbYDyA?si=1WGn2Gb5bYBjx8M"},
        {"number":"13","answer":"C","url":"https://www.youtube-nocookie.com/embed/UsFCsRbYDyA?si=1WGn2Gb5bYBjx8M"},
        {"number":"14","answer":"D","url":"https://www.youtube-nocookie.com/embed/UsFCsRbYDyA?si=1WGn2Gb5bYBjx8M"},
        {"number":"15","answer":"B","url":"https://www.youtube-nocookie.com/embed/UsFCsRbYDyA?si=1WGn2Gb5bYBjx8M"},
        {"number":"16","answer":"C","url":"https://www.youtube-nocookie.com/embed/UsFCsRbYDyA?si=1WGn2Gb5bYBjx8M"},
        {"number":"17","answer":"A","url":"https://www.youtube-nocookie.com/embed/UsFCsRbYDyA?si=1WGn2Gb5bYBjx8M"},
        {"number":"18","answer":"D","url":"https://www.youtube-nocookie.com/embed/UsFCsRbYDyA?si=1WGn2Gb5bYBjx8M"},
        {"number":"19","answer":"A","url":"https://www.youtube-nocookie.com/embed/UsFCsRbYDyA?si=1WGn2Gb5bYBjx8M"},
        {"number":"20","answer":"A","url":"https://www.youtube-nocookie.com/embed/UsFCsRbYDyA?si=1WGn2Gb5bYBjx8M"},
        {"number":"21","answer":"E","url":"https://www.youtube-nocookie.com/embed/UsFCsRbYDyA?si=1WGn2Gb5bYBjx8M"},
        {"number":"22","answer":"C","url":"https://www.youtube-nocookie.com/embed/UsFCsRbYDyA?si=1WGn2Gb5bYBjx8M"},
        {"number":"23","answer":"D","url":"https://www.youtube-nocookie.com/embed/UsFCsRbYDyA?si=1WGn2Gb5bYBjx8M"},
        {"number":"24","answer":"D","url":"https://www.youtube-nocookie.com/embed/UsFCsRbYDyA?si=1WGn2Gb5bYBjx8M"},
        {"number":"25","answer":"A","url":"https://www.youtube-nocookie.com/embed/UsFCsRbYDyA?si=1WGn2Gb5bYBjx8M"}
    ]
}